{
    "Apprentice": "Mage/Elemental",
    "ApprenticeFemale": "Mage/Elemental",
    "Arcanist": "Mage/Elder",
    "ArcanistFemale": "Mage/Elder",
    "Archer": "Bows/Archer",
    "ArcherFemale": "Bows/Archer",
    "Artillery": "Bows/Artillery",
    "ArtilleryFemale": "Bows/Artillery",
    "Assassin": "Daggers/Assassin",
    "AssassinFemale": "Daggers/Assassin",
    "Bael": "Creatures",
    "BaelElder": "Creatures",
    "Barbarian": "Cavalry/Barbarian",
    "BarbarianFemale": "Cavalry/Barbarian",
    "Berserker": "Axes/Berserker",
    "BerserkerFemale": "Axes/Berserker",
    "Brigand": "Axes/Brigand",
    "BrigandFemale": "Axes/Brigand",
    "Bulwark": "Axes/Armor",
    "Bushi": "Swords/Bushi",
    "BushiFemale": "Swords/Bushi",
    "CaptainSerena": "Lances/Captain",
    "Cavalry": "Cavalry/Cavalry",
    "CavalryFemale": "Cavalry/Cavalry",
    "Clergy": "Mage/Holy",
    "ClergyFemale": "Mage/Holy",
    "Commander": "Special",
    "Dancer": "Special/Dancer",
    "DireWolf": "Creatures",
    "Doctor": "Mage/Holy",
    "DoctorFemale": "Mage/Holy",
    "Drakoor": "Flying/Drake",
    "Fencer": "Lances/Fencer",
    "FencerFemale": "Lances/Fencer",
    "Forester": "Axes",
    "Gladiator": "Axes/Gladiator",
    "GladiatorFemale": "Axes/Gladiator",
    "Guard": "Axes/Armor",
    "Heretic": "Flying/Pegasus",
    "Hunter": "Bows/Hunter",
    "HunterFemale": "Bows/Hunter",
    "Lady": "Special/Lords",
    "Lancer": "Lances/Lancer",
    "LancerFemale": "Lances/Lancer",
    "Lieutenant": "Special/Lords",
    "LieutenantArmorless": "Special/Lords",
    "Mage": "Mage/Elemental",
    "MageFemale": "Mage/Elemental",
    "MageLord": "Mage",
    "MageLordFemale": "Mage",
    "MagicCorps": "Mage/Cavalry",
    "MagicCorpsFemale": "Mage/Cavalry",
    "Marksman": "Bows/Marksman",
    "MarksmanFemale": "Bows/Marksman",
    "Mercenary": "Swords/Mercenary",
    "MercenaryFemale": "Swords/Mercenary",
    "Miko": "Mage/Elder",
    "Militia": "Lances/Militia",
    "MilitiaFemale": "Lances/Militia",
    "Myrmidon": "Swords/Myrmidons",
    "MyrmidonFemale": "Swords/Myrmidons",
    "MyrmidonLongHair": "Swords/Myrmidons",
    "Nomad": "Swords/Myrmidons",
    "NomadFemale": "Swords/Myrmidons",
    "Nurse": "Mage/Holy",
    "NurseMale": "Mage/Holy",
    "Paladin": "Cavalry/Paladin",
    "PaladinFemale": "Cavalry/Paladin",
    "PegasusKnight": "Flying/Pegasus",
    "Pioneer": "Axes/Pioneer",
    "PioneerFemale": "Axes/Pioneer",
    "Pirate": "Axes/Pirate",
    "PirateFemale": "Axes/Pirate",
    "PirateFemaleThin": "Axes/Pirate",
    "PirateStubs": "Axes/Pirate",
    "Priestess": "Special",
    "Prior": "Mage/Holy",
    "PriorFemale": "Mage/Holy",
    "Privateer": "Axes/Privateer",
    "PrivateerFemale": "Axes/Privateer",
    "Ranger": "Cavalry/Ranger",
    "RangerFemale": "Cavalry/Ranger",
    "Sage": "Mage/Elemental",
    "SageFemale": "Mage/Elemental",
    "Sargeant": "Lances/Sargeant",
    "SargeantFemale": "Lances/Sargeant",
    "Savage": "Axes/Savage",
    "SavageFemale": "Axes/Savage",
    "Scholar": "Mage/Elder",
    "ScholarFemale": "Mage/Elder",
    "Scout": "Cavalry/Scout",
    "ScoutFemale": "Cavalry/Scout",
    "ShamanFemale": "Mage/Elder",
    "ShamanMale": "Mage/Elder",
    "Shinobi": "Daggers/Shinobi",
    "ShinobiFemale": "Daggers/Shinobi",
    "Shintaku": "Mage/Elder",
    "SkyLord": "Flying/Sky Lord",
    "SkyLordFemale": "Flying/Sky Lord",
    "SkyWyrm": "Creatures",
    "Sniper": "Bows/Sniper",
    "SniperFemale": "Bows/Sniper",
    "Soldier": "Lances/Soldier",
    "SoldierFemale": "Lances/Soldier",
    "Tactician": "Mage/Cavalry",
    "TacticianMale": "Mage/Cavalry",
    "Valkyrie": "Flying/Pegasus",
    "Vidame": "Flying/Drake",
    "Villager": "Special/Villager",
    "VillagerFemale": "Special/Villager",
    "WildWyvern": "Creatures",
    "Wolf": "Creatures",
    "WolfKnight": "Cavalry/Wolf Knight",
    "WolfNomad": "Cavalry/Wolf Nomad",
    "WolfNomadFemale": "Cavalry/Wolf Nomad"
}